setup.py
anillo/__init__.py
anillo/app.py
anillo/serving.py
anillo.egg-info/PKG-INFO
anillo.egg-info/SOURCES.txt
anillo.egg-info/dependency_links.txt
anillo.egg-info/requires.txt
anillo.egg-info/top_level.txt
anillo/adapters/__init__.py
anillo/adapters/anillo.py
anillo/adapters/base.py
anillo/adapters/werkzeug.py
anillo/handlers/__init__.py
anillo/handlers/mount.py
anillo/handlers/routing.py
anillo/http/__init__.py
anillo/http/request.py
anillo/http/responses.py
anillo/middlewares/__init__.py
anillo/middlewares/cookies.py
anillo/middlewares/cors.py
anillo/middlewares/default_headers.py
anillo/middlewares/exception_handler.py
anillo/middlewares/json.py
anillo/middlewares/multipart_params.py
anillo/middlewares/params.py
anillo/middlewares/session.py
anillo/utils/__init__.py
anillo/utils/common.py
anillo/utils/multipart.py
anillo/utils/structures.py
tests/__init__.py