Metadata-Version: 1.1
Name: anillo
Version: 0.1.4
Summary: Ring/compojure like nanoframework build on top of werkzeug
Home-page: https://github.com/jespino/anillo
Author: Jesús Espino García
Author-email: jespinog@gmail.com
License: BSD
Keywords: framework,web,ring,compojure
Platform: UNKNOWN
Classifier: Programming Language :: Python
Classifier: Programming Language :: Python :: 3
Classifier: Programming Language :: Python :: 3.3
Classifier: Programming Language :: Python :: 3.4
Classifier: Development Status :: 3 - Alpha
Classifier: Intended Audience :: Developers
Classifier: License :: OSI Approved :: BSD License
Classifier: Operating System :: OS Independent
Classifier: Programming Language :: Python
Classifier: Topic :: Internet :: WWW/HTTP
